.gitignore
.travis.yml
CHANGES.rst
LICENSE
MANIFEST.in
README.rst
setup.py
claviger.egg-info/PKG-INFO
claviger.egg-info/SOURCES.txt
claviger.egg-info/dependency_links.txt
claviger.egg-info/entry_points.txt
claviger.egg-info/not-zip-safe
claviger.egg-info/requires.txt
claviger.egg-info/top_level.txt
docs/return-codes.yml
src/__init__.py
src/authorized_keys.py
src/config.py
src/config.schema.yml
src/main.py
src/scp.py
src/worker.py
src/tests/__init__.py
src/tests/test_authorized_keys.py