Metadata-Version: 1.0
Name: claviger
Version: 0.1.2
Summary: Synchronizes remote SSH authorized_keys
Home-page: http://github.com/bwesterb/claviger/
Author: Bas Westerbaan
Author-email: bas@westerbaan.name
License: GPL 3.0
Platform: UNKNOWN
